evt/__init__.py
evt/dataset.py
evt/utils.py
evt/_compiled_expressions/__init__.py
evt/_compiled_expressions/compiled_expressions.py
evt/estimators/__init__.py
evt/estimators/estimator_abc.py
evt/estimators/gevmle.py
evt/estimators/gpdmle.py
evt/estimators/hill.py
evt/estimators/moment.py
evt/methods/__init__.py
evt/methods/block_maxima.py
evt/methods/peaks_over_threshold.py
evt-0.0.2.dist-info/LICENSE
evt-0.0.2.dist-info/METADATA
evt-0.0.2.dist-info/WHEEL
evt-0.0.2.dist-info/top_level.txt
evt-0.0.2.dist-info/RECORD
