Metadata-Version: 2.1
Name: evt
Version: 0.0.2
Summary: Estimators and analysis for extreme value theory (EVT)
Home-page: https://github.com/spmvg/evt
Author: Steven van Gemert
Author-email: steven@vangemert.dev
License: UNKNOWN
Platform: UNKNOWN
Requires-Python: >=3.7
License-File: LICENSE
Requires-Dist: matplotlib (>=3.4)
Requires-Dist: numpy (>=1.20)
Requires-Dist: pandas (>=1.2)
Requires-Dist: scipy (>=1.6)
